{"reporter":"","hoardings":[{"Height":5000,"Width":5000,"use":true,"brand":"lomejoooooor"},{"Height":955,"Width":300,"use":true,"brand":"Auctor Quis Tristique Corp."},{"Height":937,"Width":234,"use":true,"brand":"Hendrerit Institute"},{"Height":498,"Width":338,"use":false,"brand":"Risus Morbi LLC"},{"Height":266,"Width":593,"use":false,"brand":"Ac Metus Incorporated"},{"Height":655,"Width":180,"use":true,"brand":"Sociis Natoque Corporation"},{"Height":508,"Width":487,"use":true,"brand":"Neque Industries"},{"Height":729,"Width":316,"use":true,"brand":"Dui Fusce Aliquam Consulting"},{"Height":258,"Width":404,"use":false,"brand":"In Ltd"},{"Height":906,"Width":213,"use":false,"brand":"Orci Associates"},{"Height":810,"Width":194,"use":false,"brand":"Sed Neque Sed Corp."},{"Height":340,"Width":254,"use":true,"brand":"Est Mollis Ltd"},{"Height":898,"Width":395,"use":true,"brand":"Nonummy Ultricies Associates"},{"Height":273,"Width":296,"use":true,"brand":"Commodo Tincidunt Nibh Associates"},{"Height":463,"Width":358,"use":true,"brand":"Et Corporation"},{"Height":338,"Width":290,"use":true,"brand":"Aenean Incorporated"},{"Height":512,"Width":269,"use":true,"brand":"Mauris Consulting"},{"Height":976,"Width":415,"use":false,"brand":"Arcu Vestibulum Foundation"},{"Height":686,"Width":116,"use":true,"brand":"Tincidunt Corporation"},{"Height":717,"Width":393,"use":true,"brand":"Libero At Incorporated"},{"Height":867,"Width":548,"use":false,"brand":"Erat Eget Tincidunt PC"},{"Height":410,"Width":517,"use":false,"brand":"A Aliquet Vel Consulting"},{"Height":630,"Width":144,"use":true,"brand":"Suspendisse Company"},{"Height":373,"Width":153,"use":true,"brand":"Nonummy Ac Associates"},{"Height":861,"Width":167,"use":true,"brand":"Integer In Foundation"},{"Height":592,"Width":449,"use":true,"brand":"Dui Semper Et Industries"},{"Height":497,"Width":131,"use":true,"brand":"Iaculis Corp."},{"Height":726,"Width":600,"use":true,"brand":"Nec Tellus Nunc Consulting"},{"Height":976,"Width":470,"use":false,"brand":"Rutrum Lorem LLP"},{"Height":969,"Width":230,"use":false,"brand":"Sed Libero Proin LLC"},{"Height":711,"Width":316,"use":false,"brand":"A Mi Fringilla PC"},{"Height":400,"Width":599,"use":true,"brand":"Sed Est Nunc Ltd"},{"Height":431,"Width":454,"use":false,"brand":"Mauris Ut Mi Institute"},{"Height":448,"Width":136,"use":true,"brand":"Vel Corp."},{"Height":576,"Width":537,"use":false,"brand":"Commodo Limited"},{"Height":622,"Width":196,"use":false,"brand":"Nulla Ante Iaculis Company"},{"Height":384,"Width":219,"use":true,"brand":"Risus Donec Egestas Incorporated"},{"Height":662,"Width":346,"use":false,"brand":"Enim Nec LLP"},{"Height":614,"Width":565,"use":false,"brand":"Eu Foundation"},{"Height":401,"Width":151,"use":false,"brand":"Libero Nec Ligula Limited"},{"Height":384,"Width":460,"use":false,"brand":"Sagittis Inc."},{"Height":606,"Width":260,"use":true,"brand":"Sociis Ltd"},{"Height":520,"Width":514,"use":true,"brand":"Consequat Dolor Vitae LLP"},{"Height":900,"Width":217,"use":true,"brand":"Et Ultrices Foundation"},{"Height":250,"Width":516,"use":false,"brand":"Leo Institute"},{"Height":534,"Width":588,"use":false,"brand":"Vivamus Consulting"},{"Height":825,"Width":557,"use":false,"brand":"Lacus Limited"},{"Height":727,"Width":431,"use":false,"brand":"Augue Ac Ipsum LLP"},{"Height":685,"Width":535,"use":false,"brand":"Dolor Dapibus Gravida Incorporated"},{"Height":385,"Width":312,"use":true,"brand":"Amet Risus Donec Corporation"},{"Height":955,"Width":300,"use":true,"brand":"Auctor Quis Tristique Corp."},{"Height":937,"Width":234,"use":true,"brand":"Hendrerit Institute"},{"Height":498,"Width":338,"use":false,"brand":"Risus Morbi LLC"},{"Height":266,"Width":593,"use":false,"brand":"Ac Metus Incorporated"},{"Height":655,"Width":180,"use":true,"brand":"Sociis Natoque Corporation"},{"Height":508,"Width":487,"use":true,"brand":"Neque Industries"},{"Height":729,"Width":316,"use":true,"brand":"Dui Fusce Aliquam Consulting"},{"Height":258,"Width":404,"use":false,"brand":"In Ltd"},{"Height":906,"Width":213,"use":false,"brand":"Orci Associates"},{"Height":810,"Width":194,"use":false,"brand":"Sed Neque Sed Corp."},{"Height":340,"Width":254,"use":true,"brand":"Est Mollis Ltd"},{"Height":898,"Width":395,"use":true,"brand":"Nonummy Ultricies Associates"},{"Height":273,"Width":296,"use":true,"brand":"Commodo Tincidunt Nibh Associates"},{"Height":463,"Width":358,"use":true,"brand":"Et Corporation"},{"Height":338,"Width":290,"use":true,"brand":"Aenean Incorporated"},{"Height":512,"Width":269,"use":true,"brand":"Mauris Consulting"},{"Height":976,"Width":415,"use":false,"brand":"Arcu Vestibulum Foundation"},{"Height":686,"Width":116,"use":true,"brand":"Tincidunt Corporation"},{"Height":717,"Width":393,"use":true,"brand":"Libero At Incorporated"},{"Height":867,"Width":548,"use":false,"brand":"Erat Eget Tincidunt PC"},{"Height":410,"Width":517,"use":false,"brand":"A Aliquet Vel Consulting"},{"Height":630,"Width":144,"use":true,"brand":"Suspendisse Company"},{"Height":373,"Width":153,"use":true,"brand":"Nonummy Ac Associates"},{"Height":861,"Width":167,"use":true,"brand":"Integer In Foundation"},{"Height":592,"Width":449,"use":true,"brand":"Dui Semper Et Industries"},{"Height":497,"Width":131,"use":true,"brand":"Iaculis Corp."},{"Height":726,"Width":600,"use":true,"brand":"Nec Tellus Nunc Consulting"},{"Height":976,"Width":470,"use":false,"brand":"Rutrum Lorem LLP"},{"Height":969,"Width":230,"use":false,"brand":"Sed Libero Proin LLC"},{"Height":711,"Width":316,"use":false,"brand":"A Mi Fringilla PC"},{"Height":400,"Width":599,"use":true,"brand":"Sed Est Nunc Ltd"},{"Height":431,"Width":454,"use":false,"brand":"Mauris Ut Mi Institute"},{"Height":448,"Width":136,"use":true,"brand":"Vel Corp."},{"Height":576,"Width":537,"use":false,"brand":"Commodo Limited"},{"Height":622,"Width":196,"use":false,"brand":"Nulla Ante Iaculis Company"},{"Height":384,"Width":219,"use":true,"brand":"Risus Donec Egestas Incorporated"},{"Height":662,"Width":346,"use":false,"brand":"Enim Nec LLP"},{"Height":614,"Width":565,"use":false,"brand":"Eu Foundation"},{"Height":401,"Width":151,"use":false,"brand":"Libero Nec Ligula Limited"},{"Height":384,"Width":460,"use":false,"brand":"Sagittis Inc."},{"Height":606,"Width":260,"use":true,"brand":"Sociis Ltd"},{"Height":520,"Width":514,"use":true,"brand":"Consequat Dolor Vitae LLP"},{"Height":900,"Width":217,"use":true,"brand":"Et Ultrices Foundation"},{"Height":250,"Width":516,"use":false,"brand":"Leo Institute"},{"Height":534,"Width":588,"use":false,"brand":"Vivamus Consulting"},{"Height":825,"Width":557,"use":false,"brand":"Lacus Limited"},{"Height":727,"Width":431,"use":false,"brand":"Augue Ac Ipsum LLP"},{"Height":685,"Width":535,"use":false,"brand":"Dolor Dapibus Gravida Incorporated"},{"Height":385,"Width":312,"use":true,"brand":"Amet Risus Donec Corporation"},{"Height":5000,"Width":5000,"use":false,"brand":"lomejooooor"},{"Height":955,"Width":300,"use":true,"brand":"Auctor Quis Tristique Corp."},{"Height":937,"Width":234,"use":true,"brand":"Hendrerit Institute"},{"Height":498,"Width":338,"use":false,"brand":"Risus Morbi LLC"},{"Height":266,"Width":593,"use":false,"brand":"Ac Metus Incorporated"},{"Height":655,"Width":180,"use":true,"brand":"Sociis Natoque Corporation"},{"Height":508,"Width":487,"use":true,"brand":"Neque Industries"},{"Height":729,"Width":316,"use":true,"brand":"Dui Fusce Aliquam Consulting"},{"Height":258,"Width":404,"use":false,"brand":"In Ltd"},{"Height":906,"Width":213,"use":false,"brand":"Orci Associates"},{"Height":810,"Width":194,"use":false,"brand":"Sed Neque Sed Corp."},{"Height":340,"Width":254,"use":true,"brand":"Est Mollis Ltd"},{"Height":898,"Width":395,"use":true,"brand":"Nonummy Ultricies Associates"},{"Height":273,"Width":296,"use":true,"brand":"Commodo Tincidunt Nibh Associates"},{"Height":463,"Width":358,"use":true,"brand":"Et Corporation"},{"Height":338,"Width":290,"use":true,"brand":"Aenean Incorporated"},{"Height":512,"Width":269,"use":true,"brand":"Mauris Consulting"},{"Height":976,"Width":415,"use":false,"brand":"Arcu Vestibulum Foundation"},{"Height":686,"Width":116,"use":true,"brand":"Tincidunt Corporation"},{"Height":717,"Width":393,"use":true,"brand":"Libero At Incorporated"},{"Height":867,"Width":548,"use":false,"brand":"Erat Eget Tincidunt PC"},{"Height":410,"Width":517,"use":false,"brand":"A Aliquet Vel Consulting"},{"Height":630,"Width":144,"use":true,"brand":"Suspendisse Company"},{"Height":373,"Width":153,"use":true,"brand":"Nonummy Ac Associates"},{"Height":861,"Width":167,"use":true,"brand":"Integer In Foundation"},{"Height":592,"Width":449,"use":true,"brand":"Dui Semper Et Industries"},{"Height":497,"Width":131,"use":true,"brand":"Iaculis Corp."},{"Height":726,"Width":600,"use":true,"brand":"Nec Tellus Nunc Consulting"},{"Height":976,"Width":470,"use":false,"brand":"Rutrum Lorem LLP"},{"Height":969,"Width":230,"use":false,"brand":"Sed Libero Proin LLC"},{"Height":711,"Width":316,"use":false,"brand":"A Mi Fringilla PC"},{"Height":400,"Width":599,"use":true,"brand":"Sed Est Nunc Ltd"},{"Height":431,"Width":454,"use":false,"brand":"Mauris Ut Mi Institute"},{"Height":448,"Width":136,"use":true,"brand":"Vel Corp."},{"Height":576,"Width":537,"use":false,"brand":"Commodo Limited"},{"Height":622,"Width":196,"use":false,"brand":"Nulla Ante Iaculis Company"},{"Height":384,"Width":219,"use":true,"brand":"Risus Donec Egestas Incorporated"},{"Height":662,"Width":346,"use":false,"brand":"Enim Nec LLP"},{"Height":614,"Width":565,"use":false,"brand":"Eu Foundation"},{"Height":401,"Width":151,"use":false,"brand":"Libero Nec Ligula Limited"},{"Height":384,"Width":460,"use":false,"brand":"Sagittis Inc."},{"Height":606,"Width":260,"use":true,"brand":"Sociis Ltd"},{"Height":520,"Width":514,"use":true,"brand":"Consequat Dolor Vitae LLP"},{"Height":900,"Width":217,"use":true,"brand":"Et Ultrices Foundation"},{"Height":250,"Width":516,"use":false,"brand":"Leo Institute"},{"Height":534,"Width":588,"use":false,"brand":"Vivamus Consulting"},{"Height":825,"Width":557,"use":false,"brand":"Lacus Limited"},{"Height":727,"Width":431,"use":false,"brand":"Augue Ac Ipsum LLP"},{"Height":685,"Width":535,"use":false,"brand":"Dolor Dapibus Gravida Incorporated"},{"Height":385,"Width":312,"use":true,"brand":"Amet Risus Donec Corporation"},{"Height":955,"Width":300,"use":true,"brand":"Auctor Quis Tristique Corp."},{"Height":937,"Width":234,"use":true,"brand":"Hendrerit Institute"},{"Height":498,"Width":338,"use":false,"brand":"Risus Morbi LLC"},{"Height":266,"Width":593,"use":false,"brand":"Ac Metus Incorporated"},{"Height":655,"Width":180,"use":true,"brand":"Sociis Natoque Corporation"},{"Height":508,"Width":487,"use":true,"brand":"Neque Industries"},{"Height":729,"Width":316,"use":true,"brand":"Dui Fusce Aliquam Consulting"},{"Height":258,"Width":404,"use":false,"brand":"In Ltd"},{"Height":906,"Width":213,"use":false,"brand":"Orci Associates"},{"Height":810,"Width":194,"use":false,"brand":"Sed Neque Sed Corp."},{"Height":340,"Width":254,"use":true,"brand":"Est Mollis Ltd"},{"Height":898,"Width":395,"use":true,"brand":"Nonummy Ultricies Associates"},{"Height":273,"Width":296,"use":true,"brand":"Commodo Tincidunt Nibh Associates"},{"Height":463,"Width":358,"use":true,"brand":"Et Corporation"},{"Height":338,"Width":290,"use":true,"brand":"Aenean Incorporated"},{"Height":512,"Width":269,"use":true,"brand":"Mauris Consulting"},{"Height":976,"Width":415,"use":false,"brand":"Arcu Vestibulum Foundation"},{"Height":686,"Width":116,"use":true,"brand":"Tincidunt Corporation"},{"Height":717,"Width":393,"use":true,"brand":"Libero At Incorporated"},{"Height":867,"Width":548,"use":false,"brand":"Erat Eget Tincidunt PC"},{"Height":410,"Width":517,"use":false,"brand":"A Aliquet Vel Consulting"},{"Height":630,"Width":144,"use":true,"brand":"Suspendisse Company"},{"Height":373,"Width":153,"use":true,"brand":"Nonummy Ac Associates"},{"Height":861,"Width":167,"use":true,"brand":"Integer In Foundation"},{"Height":592,"Width":449,"use":true,"brand":"Dui Semper Et Industries"},{"Height":497,"Width":131,"use":true,"brand":"Iaculis Corp."},{"Height":726,"Width":600,"use":true,"brand":"Nec Tellus Nunc Consulting"},{"Height":976,"Width":470,"use":false,"brand":"Rutrum Lorem LLP"},{"Height":969,"Width":230,"use":false,"brand":"Sed Libero Proin LLC"},{"Height":711,"Width":316,"use":false,"brand":"A Mi Fringilla PC"},{"Height":400,"Width":599,"use":true,"brand":"Sed Est Nunc Ltd"},{"Height":431,"Width":454,"use":false,"brand":"Mauris Ut Mi Institute"},{"Height":448,"Width":136,"use":true,"brand":"Vel Corp."},{"Height":576,"Width":537,"use":false,"brand":"Commodo Limited"},{"Height":622,"Width":196,"use":false,"brand":"Nulla Ante Iaculis Company"},{"Height":384,"Width":219,"use":true,"brand":"Risus Donec Egestas Incorporated"},{"Height":662,"Width":346,"use":false,"brand":"Enim Nec LLP"},{"Height":614,"Width":565,"use":false,"brand":"Eu Foundation"},{"Height":401,"Width":151,"use":false,"brand":"Libero Nec Ligula Limited"},{"Height":384,"Width":460,"use":false,"brand":"Sagittis Inc."},{"Height":606,"Width":260,"use":true,"brand":"Sociis Ltd"},{"Height":520,"Width":514,"use":true,"brand":"Consequat Dolor Vitae LLP"},{"Height":900,"Width":217,"use":true,"brand":"Et Ultrices Foundation"},{"Height":250,"Width":516,"use":false,"brand":"Leo Institute"},{"Height":534,"Width":588,"use":false,"brand":"Vivamus Consulting"},{"Height":825,"Width":557,"use":false,"brand":"Lacus Limited"},{"Height":727,"Width":431,"use":false,"brand":"Augue Ac Ipsum LLP"},{"Height":685,"Width":535,"use":false,"brand":"Dolor Dapibus Gravida Incorporated"},{"Height":385,"Width":312,"use":true,"brand":"Amet Risus Donec Corporation"}]}